qpm/__init__.py
qpm/__main__.py
qpm/packaging/__init__.py
qpm/packaging/auto_argument_parser.py
qpm/packaging/driver_packager.py
qpm/packaging/drivers_packager.py
qpm/packaging/package_manager.py
qpm/packaging/quali_api_client.py
qpm/packaging/shell_installer.py
qpm/packaging/shell_packager.py
qpm/packaging/shell_publisher.py
qpm-1.20.dist-info/LICENSE
qpm-1.20.dist-info/METADATA
qpm-1.20.dist-info/WHEEL
qpm-1.20.dist-info/top_level.txt
qpm-1.20.dist-info/RECORD
