Metadata-Version: 2.1
Name: qpm
Version: 1.20
Summary: QPM is QualiSystems Package Manager
Home-page: https://github.com/QualiSystems/qpm
Author: Boris Modylevsky
Author-email: borismod@gmail.com
License: Apache 2.0
Keywords: QualiSystems
Platform: UNKNOWN
Requires-Python: >=3.6
